testcontainers/arangodb/__init__.py
tests/test_arangodb.py
testcontainers_arangodb-0.0.1rc1.dist-info/METADATA
testcontainers_arangodb-0.0.1rc1.dist-info/WHEEL
testcontainers_arangodb-0.0.1rc1.dist-info/top_level.txt
testcontainers_arangodb-0.0.1rc1.dist-info/RECORD
