Metadata-Version: 2.1
Name: testcontainers-arangodb
Version: 0.0.1rc1
Summary: Arango DB component of testcontainers-python.
Home-page: https://github.com/testcontainers/testcontainers-python
Requires-Python: >=3.7
Requires-Dist: testcontainers-core
Requires-Dist: python-arango
